requestlog/__init__.py
requestlog/apps.py
requestlog/middleware.py
requestlog/models.py
requestlog/tasks.py
requestlog/utils.py
requestlog/migrations/0001_initial_squashed_0005_auto_20180717_2255.py
requestlog/migrations/0002_requestlog_status_code_squashed_0004_auto_20180718_0811.py
requestlog/migrations/0003_requestlog_response_snippet.py
requestlog/migrations/0004_auto_20210625_1551.py
requestlog/migrations/0005_auto_20211003_1245.py
requestlog/migrations/__init__.py
requestlog/tests/__init__.py
requestlog/tests/tests.py
django_requestlog-1.1.8.dist-info/LICENSE
django_requestlog-1.1.8.dist-info/METADATA
django_requestlog-1.1.8.dist-info/WHEEL
django_requestlog-1.1.8.dist-info/top_level.txt
django_requestlog-1.1.8.dist-info/RECORD
