Metadata-Version: 2.1
Name: django-requestlog
Version: 1.1.8
Summary: Middleware to log http requests to postgresql
Home-page: https://github.com/muehlemann-popp/requestlog
Author: Silvan Mühlemann
Author-email: silvan.muehlemann@muehlemann-popp.ch
License: MIT
Platform: UNKNOWN
Classifier: Framework :: Django
Classifier: Intended Audience :: Developers
Classifier: License :: OSI Approved :: MIT License
Classifier: Operating System :: OS Independent
Classifier: Topic :: Software Development
License-File: LICENSE
Requires-Dist: Django (>=1.9)
Requires-Dist: httplib2
Requires-Dist: psycopg2-binary
